helm_sdkpy/__init__.py
helm_sdkpy/_ffi.py
helm_sdkpy/actions.py
helm_sdkpy/chart.py
helm_sdkpy/exceptions.py
helm_sdkpy/repo.py
helm_sdkpy/_lib/linux-amd64/libhelm_sdkpy.h
helm_sdkpy/_lib/linux-amd64/libhelm_sdkpy.so
helm_sdkpy-0.0.13.dist-info/METADATA
helm_sdkpy-0.0.13.dist-info/WHEEL
helm_sdkpy-0.0.13.dist-info/licenses/LICENSE
helm_sdkpy-0.0.13.dist-info/RECORD
