Metadata-Version: 2.4
Name: helm-sdkpy
Version: 0.0.13
Summary: Python bindings for Helm - The Kubernetes Package Manager
Author: VantageCompute
License: Apache-2.0
License-File: LICENSE
Keywords: bindings,helm,k8s,kubernetes,package-manager
Classifier: License :: OSI Approved :: Apache Software License
Classifier: Programming Language :: Python :: 3
Classifier: Programming Language :: Python :: 3.12
Classifier: Topic :: Software Development :: Libraries :: Python Modules
Classifier: Topic :: System :: Systems Administration
Requires-Python: >=3.12
Requires-Dist: cffi>=1.15
Provides-Extra: dev
Requires-Dist: codespell; extra == 'dev'
Requires-Dist: coverage[toml]~=7.8; extra == 'dev'
Requires-Dist: pyright; extra == 'dev'
Requires-Dist: pytest-asyncio~=0.24; extra == 'dev'
Requires-Dist: pytest-mock~=3.14; extra == 'dev'
Requires-Dist: pytest-order~=1.3; extra == 'dev'
Requires-Dist: pytest~=8.3; extra == 'dev'
Requires-Dist: python-dotenv~=1.0; extra == 'dev'
Requires-Dist: ruff; extra == 'dev'
